{"energy_band_ratio":{"tapa_medio_0":0.0126598226},"inharmonicity":{"tapa_medio_0":1.0},"max_mag_freq":{"tapa_medio_0":113.371391296},"spectral_centroid_time":{"tapa_medio_0":8848.94726562},"spectral_complexity":{"tapa_medio_0":100.0},"spectral_contrast_max":{"tapa_medio_0":-1.2946884632},"spectral_contrast_mean":{"tapa_medio_0":-1.6687620878},"spectral_contrast_median":{"tapa_medio_0":-1.483453393},"spectral_contrast_min":{"tapa_medio_0":-2.5635633469},"spectral_contrast_stdev":{"tapa_medio_0":0.4249670804},"spectral_peaks_freq_max":{"tapa_medio_0":678.791931152},"spectral_peaks_freq_mean":{"tapa_medio_0":309.849914551},"spectral_peaks_freq_median":{"tapa_medio_0":289.590179443},"spectral_peaks_freq_min":{"tapa_medio_0":4.5637793541},"spectral_peaks_freq_stdev":{"tapa_medio_0":182.409240723},"spectral_peaks_mag_max":{"tapa_medio_0":106.327522278},"spectral_peaks_mag_mean":{"tapa_medio_0":44.7109184265},"spectral_peaks_mag_median":{"tapa_medio_0":39.1743202209},"spectral_peaks_mag_min":{"tapa_medio_0":10.6029872894},"spectral_peaks_mag_stdev":{"tapa_medio_0":20.2908439636},"spectral_valley_max":{"tapa_medio_0":3.0662488937},"spectral_valley_mean":{"tapa_medio_0":1.9335004091},"spectral_valley_median":{"tapa_medio_0":1.9820352793},"spectral_valley_min":{"tapa_medio_0":0.7654696703},"spectral_valley_stdev":{"tapa_medio_0":0.6821247935},"spectral_whitening_max":{"tapa_medio_0":0.9714069962},"spectral_whitening_mean":{"tapa_medio_0":0.6526353359},"spectral_whitening_median":{"tapa_medio_0":0.6571933031},"spectral_whitening_min":{"tapa_medio_0":0.2717631459},"spectral_whitening_stdev":{"tapa_medio_0":0.1778872013},"strong_peak":{"tapa_medio_0":2377.51977539},"target":{"tapa_medio_0":1.0}}